krishang_HDS/__init__.py
krishang_HDS-0.0.2.dist-info/LICENSE
krishang_HDS-0.0.2.dist-info/METADATA
krishang_HDS-0.0.2.dist-info/WHEEL
krishang_HDS-0.0.2.dist-info/top_level.txt
krishang_HDS-0.0.2.dist-info/RECORD
