Metadata-Version: 2.1
Name: krishang-HDS
Version: 0.0.2
Summary: Decline in transcriptional homeostasis defines aging
Home-page: https://github.com/krishan57gupta/HDS
Author: Krishan Gupta, Princey Yadav, Debarka Sengupta
Author-email: krishang@iiitd.ac.in
License: UNKNOWN
Platform: UNKNOWN
Classifier: Programming Language :: Python :: 3
Classifier: License :: OSI Approved :: MIT License
Classifier: Operating System :: OS Independent
Requires-Python: >=3.6
